CHANGES.txt
LICENSE.txt
bootstrap.py
buildout.cfg
setup.py
docs/CREDITS.txt
docs/README.txt
src/megrok/__init__.py
src/megrok.kss.egg-info/PKG-INFO
src/megrok.kss.egg-info/SOURCES.txt
src/megrok.kss.egg-info/dependency_links.txt
src/megrok.kss.egg-info/entry_points.txt
src/megrok.kss.egg-info/namespace_packages.txt
src/megrok.kss.egg-info/not-zip-safe
src/megrok.kss.egg-info/requires.txt
src/megrok.kss.egg-info/top_level.txt
src/megrok/kss/__init__.py
src/megrok/kss/components.py
src/megrok/kss/configure.zcml
src/megrok/kss/integration.zcml
src/megrok/kss/interfaces.py
src/megrok/kss/meta.py
src/megrok/kss/testing.py
src/megrok/kss/doc/README.txt
src/megrok/kss/tests/__init__.py
src/megrok/kss/tests/kss.py
src/megrok/kss/tests/test_integration.py