Metadata-Version: 1.0
Name: megrok.kss
Version: 0.2.3
Summary: KSS for Grok. Ajax with Style, see http://kssproject.org
Home-page: http://pypi.python.org/pypi/megrok.kss
Author: Godefroid Chapelle
Author-email: gotcha@bubblenet.be
License: ZPL
Platform: UNKNOWN
